<?xml version="1.0" encoding="UTF-8"?>
<!DOCTYPE suite SYSTEM "http://testng.org/testng-1.0.dtd">
 <suite name="Suite" parallel="none">
 
    <test name="Login">
  <parameter name="testname" value="TestScripts/HomePage/ApplicationLogin.xlsx"/>
    <classes>
      <class name="org.automation.main.StartExecution"/>
    </classes>
  </test> 
  
<!--       <test name="TEST2">
  <parameter name="testname" value="TestScripts/HomePage/test2.xlsx"/>
    <classes>
      <class name="org.automation.main.StartExecution"/>
    </classes>
  </test>  -->
  
  
  </suite>